README.md
setup.cfg
setup.py
pypki2/__init__.py
pypki2/exceptions.py
pypki2/pypki2.py
pypki2.egg-info/PKG-INFO
pypki2.egg-info/SOURCES.txt
pypki2.egg-info/dependency_links.txt
pypki2.egg-info/requires.txt
pypki2.egg-info/top_level.txt
pypki2config/__init__.py
pypki2config/config.py
pypki2config/exceptions.py
pypki2config/p12.py
pypki2config/pem.py
pypki2config/utils.py
pypki2pip/__init__.py
pypki2pip/exceptions.py
pypki2pip/wrapper.py