Metadata-Version: 1.2
Name: pypki2
Version: 0.10.0
Summary: More user-friendly way to access PKI-enabled services
Home-page: https://github.com/nbgallery/pypki2
Author: Bill Allen
Author-email: photo.allen@gmail.com
License: UNKNOWN
Keywords: pki,ssl,pem,pkcs12,p12,mypki,pip
Platform: UNKNOWN
Requires-Python: >=2.7.9, !=3.0.*, !=3.1.*, !=3.2.*, !=3.3.*, <4
